kstopit/__init__.py
kstopit/kstopit.py
kstopit/timeout_type.py
kstopit-0.0.16.dist-info/METADATA
kstopit-0.0.16.dist-info/WHEEL
kstopit-0.0.16.dist-info/top_level.txt
kstopit-0.0.16.dist-info/RECORD
