Metadata-Version: 2.1
Name: kstopit
Version: 0.0.16
Summary: kstopit
Home-page: https://github.com/kkristof200/py_kstopit
Author: Kristof
Classifier: Programming Language :: Python :: 3
Classifier: License :: OSI Approved :: MIT License
Classifier: Operating System :: OS Independent
Requires-Python: >=3.5
